<annotation>
	<folder>car</folder>
	<filename>AX 9984 AT.jpg</filename>
	<path>/home/dsokol/Downloads/linux_v1.4.3/data/car/AX 9984 AT.jpg</path>
	<source>
		<database>Unknown</database>
	</source>
	<size>
		<width>640</width>
		<height>448</height>
		<depth>3</depth>
	</size>
	<segmented>0</segmented>
	<object>
		<name>car</name>
		<pose>Unspecified</pose>
		<truncated>0</truncated>
		<difficult>0</difficult>
		<bndbox>
			<xmin>22</xmin>
			<ymin>83</ymin>
			<xmax>621</xmax>
			<ymax>420</ymax>
		</bndbox>
	</object>
	<object>
		<name>plate</name>
		<pose>Unspecified</pose>
		<truncated>0</truncated>
		<difficult>1</difficult>
		<bndbox>
			<xmin>454</xmin>
			<ymin>267</ymin>
			<xmax>567</xmax>
			<ymax>301</ymax>
		</bndbox>
	</object>
</annotation>
